pptx2md/__init__.py
pptx2md/__main__.py
pptx2md/entry.py
pptx2md/image.py
pptx2md/log.py
pptx2md/multi_column.py
pptx2md/outputter.py
pptx2md/parser.py
pptx2md/types.py
pptx2md/utils.py
pptx_to_md-1.0.1.dist-info/LICENSE
pptx_to_md-1.0.1.dist-info/METADATA
pptx_to_md-1.0.1.dist-info/WHEEL
pptx_to_md-1.0.1.dist-info/entry_points.txt
pptx_to_md-1.0.1.dist-info/RECORD
